CHANGES.rst
README.rst
setup.py
supervisord-sample.conf
jb/__init__.py
jb.recipe.supervisor.egg-info/PKG-INFO
jb.recipe.supervisor.egg-info/SOURCES.txt
jb.recipe.supervisor.egg-info/dependency_links.txt
jb.recipe.supervisor.egg-info/entry_points.txt
jb.recipe.supervisor.egg-info/namespace_packages.txt
jb.recipe.supervisor.egg-info/not-zip-safe
jb.recipe.supervisor.egg-info/requires.txt
jb.recipe.supervisor.egg-info/top_level.txt
jb/recipe/__init__.py
jb/recipe/supervisor/__init__.py