Metadata-Version: 1.1
Name: jb.recipe.supervisor
Version: 0.0.1
Summary: Recipe for installing Supervisor
Home-page: https://github.com/multani/jb.recipe.supervisor
Author: Jonathan Ballet
Author-email: jon@multani.info
License: BSD
Keywords: buildout recipe supervisor template
Platform: UNKNOWN
Classifier: Development Status :: 3 - Alpha
Classifier: Framework :: Buildout
Classifier: Intended Audience :: System Administrators
Classifier: License :: OSI Approved :: BSD License
Classifier: Topic :: Software Development :: Build Tools
Classifier: Topic :: System :: Systems Administration
